setup.py
pysander/__init__.py
pysander/auth.py
pysander/context.py
pysander/hosting.py
pysander/queries.py
pysander/repositories.py
pysander/sql.py
pysander/sqlauditrepo.py
pysander/sqlrepo.py
pysander/utils.py
pysander/validation.py
pysander/validators.py
pysander.egg-info/PKG-INFO
pysander.egg-info/SOURCES.txt
pysander.egg-info/dependency_links.txt
pysander.egg-info/requires.txt
pysander.egg-info/top_level.txt