Metadata-Version: 1.1
Name: pysander
Version: 0.1.1.dev1
Summary: A python framework for building RESTful crud APIs
Home-page: https://bitbucket.org/lvanspronsen/pysander
Author: Loren Van Spronsen
Author-email: lorenvs@outlook.com
License: MIT
Platform: UNKNOWN
Classifier: Development Status :: 3 - Alpha
Classifier: Intended Audience :: Developers
Classifier: License :: OSI Approved :: MIT License
Classifier: Programming Language :: Python :: 3.3
